{
  "demo/docs/get-started.mdx": {
    "inboundLinks": 8,
    "outboundLinks": 5,
    "importedBy": 0,
    "navDepth": 2,
    "orphanNav": false,
    "orphanLinks": false,
    "orphanTrue": false,
    "orphanReference": false,
    "deepNav": false,
    "hubScore": 8,
    "deadEnd": false,
    "deadEndScore": 8
  },
  "demo/docs/authenticate.mdx": {
    "inboundLinks": 6,
    "outboundLinks": 4,
    "importedBy": 0,
    "navDepth": 2,
    "orphanNav": false,
    "orphanLinks": false,
    "orphanTrue": false,
    "orphanReference": false,
    "deepNav": false,
    "hubScore": 6,
    "deadEnd": false,
    "deadEndScore": 6
  },
  "demo/docs/secure.mdx": {
    "inboundLinks": 5,
    "outboundLinks": 3,
    "importedBy": 0,
    "navDepth": 2,
    "orphanNav": false,
    "orphanLinks": false,
    "orphanTrue": false,
    "orphanReference": false,
    "deepNav": false,
    "hubScore": 5,
    "deadEnd": false,
    "deadEndScore": 5
  },
  "demo/docs/manage-users.mdx": {
    "inboundLinks": 4,
    "outboundLinks": 3,
    "importedBy": 0,
    "navDepth": 2,
    "orphanNav": false,
    "orphanLinks": false,
    "orphanTrue": false,
    "orphanReference": false,
    "deepNav": false,
    "hubScore": 4,
    "deadEnd": false,
    "deadEndScore": 4
  },
  "demo/docs/customize.mdx": {
    "inboundLinks": 7,
    "outboundLinks": 4,
    "importedBy": 0,
    "navDepth": 2,
    "orphanNav": false,
    "orphanLinks": false,
    "orphanTrue": false,
    "orphanReference": false,
    "deepNav": false,
    "hubScore": 7,
    "deadEnd": false,
    "deadEndScore": 7
  },
  "demo/docs/get-started/applications.mdx": {
    "inboundLinks": 3,
    "outboundLinks": 2,
    "importedBy": 0,
    "navDepth": 3,
    "orphanNav": false,
    "orphanLinks": false,
    "orphanTrue": false,
    "orphanReference": false,
    "deepNav": false,
    "hubScore": 3,
    "deadEnd": false,
    "deadEndScore": 3
  },
  "demo/docs/get-started/apis.mdx": {
    "inboundLinks": 4,
    "outboundLinks": 2,
    "importedBy": 0,
    "navDepth": 3,
    "orphanNav": false,
    "orphanLinks": false,
    "orphanTrue": false,
    "orphanReference": false,
    "deepNav": false,
    "hubScore": 4,
    "deadEnd": false,
    "deadEndScore": 4
  },
  "demo/docs/authenticate/oidc.mdx": {
    "inboundLinks": 5,
    "outboundLinks": 2,
    "importedBy": 0,
    "navDepth": 3,
    "orphanNav": false,
    "orphanLinks": false,
    "orphanTrue": false,
    "orphanReference": false,
    "deepNav": false,
    "hubScore": 5,
    "deadEnd": false,
    "deadEndScore": 5
  },
  "demo/docs/authenticate/oauth2.mdx": {
    "inboundLinks": 6,
    "outboundLinks": 3,
    "importedBy": 0,
    "navDepth": 3,
    "orphanNav": false,
    "orphanLinks": false,
    "orphanTrue": false,
    "orphanReference": false,
    "deepNav": false,
    "hubScore": 6,
    "deadEnd": false,
    "deadEndScore": 6
  },
  "demo/docs/secure/tokens.mdx": {
    "inboundLinks": 4,
    "outboundLinks": 2,
    "importedBy": 0,
    "navDepth": 3,
    "orphanNav": false,
    "orphanLinks": false,
    "orphanTrue": false,
    "orphanReference": false,
    "deepNav": false,
    "hubScore": 4,
    "deadEnd": false,
    "deadEndScore": 4
  },
  "demo/docs/secure/tokens/access-tokens.mdx": {
    "inboundLinks": 3,
    "outboundLinks": 1,
    "importedBy": 0,
    "navDepth": 4,
    "orphanNav": false,
    "orphanLinks": false,
    "orphanTrue": false,
    "orphanReference": false,
    "deepNav": false,
    "hubScore": 3,
    "deadEnd": false,
    "deadEndScore": 3
  },
  "demo/docs/manage-users/user-profiles.mdx": {
    "inboundLinks": 2,
    "outboundLinks": 1,
    "importedBy": 0,
    "navDepth": 3,
    "orphanNav": false,
    "orphanLinks": false,
    "orphanTrue": false,
    "orphanReference": false,
    "deepNav": false,
    "hubScore": 2,
    "deadEnd": false,
    "deadEndScore": 2
  },
  "demo/docs/customize/actions.mdx": {
    "inboundLinks": 5,
    "outboundLinks": 3,
    "importedBy": 0,
    "navDepth": 3,
    "orphanNav": false,
    "orphanLinks": false,
    "orphanTrue": false,
    "orphanReference": false,
    "deepNav": false,
    "hubScore": 5,
    "deadEnd": false,
    "deadEndScore": 5
  },
  "demo/docs/customize/rules.mdx": {
    "inboundLinks": 3,
    "outboundLinks": 1,
    "importedBy": 0,
    "navDepth": 3,
    "orphanNav": false,
    "orphanLinks": false,
    "orphanTrue": false,
    "orphanReference": false,
    "deepNav": false,
    "hubScore": 3,
    "deadEnd": false,
    "deadEndScore": 3
  },
  "demo/docs/api/management-api.mdx": {
    "inboundLinks": 4,
    "outboundLinks": 2,
    "importedBy": 0,
    "navDepth": 2,
    "orphanNav": false,
    "orphanLinks": false,
    "orphanTrue": false,
    "orphanReference": false,
    "deepNav": false,
    "hubScore": 4,
    "deadEnd": false,
    "deadEndScore": 4
  },
  "demo/docs/api/authentication-api.mdx": {
    "inboundLinks": 3,
    "outboundLinks": 2,
    "importedBy": 0,
    "navDepth": 2,
    "orphanNav": false,
    "orphanLinks": false,
    "orphanTrue": false,
    "orphanReference": false,
    "deepNav": false,
    "hubScore": 3,
    "deadEnd": false,
    "deadEndScore": 3
  },
  "demo/docs/troubleshoot.mdx": {
    "inboundLinks": 2,
    "outboundLinks": 2,
    "importedBy": 0,
    "navDepth": 2,
    "orphanNav": false,
    "orphanLinks": false,
    "orphanTrue": false,
    "orphanReference": false,
    "deepNav": false,
    "hubScore": 2,
    "deadEnd": false,
    "deadEndScore": 2
  },
  "demo/docs/troubleshoot/errors.mdx": {
    "inboundLinks": 1,
    "outboundLinks": 0,
    "importedBy": 0,
    "navDepth": 3,
    "orphanNav": false,
    "orphanLinks": false,
    "orphanTrue": false,
    "orphanReference": false,
    "deepNav": false,
    "hubScore": 1,
    "deadEnd": false,
    "deadEndScore": 1
  },
  "demo/docs/best-practices.mdx": {
    "inboundLinks": 2,
    "outboundLinks": 1,
    "importedBy": 0,
    "navDepth": 2,
    "orphanNav": false,
    "orphanLinks": false,
    "orphanTrue": false,
    "orphanReference": false,
    "deepNav": false,
    "hubScore": 2,
    "deadEnd": false,
    "deadEndScore": 2
  },
  "demo/docs/legacy-migration.mdx": {
    "inboundLinks": 0,
    "outboundLinks": 0,
    "importedBy": 0,
    "navDepth": null,
    "orphanNav": true,
    "orphanLinks": true,
    "orphanTrue": true,
    "orphanReference": false,
    "deepNav": false,
    "hubScore": 0,
    "deadEnd": false,
    "deadEndScore": 0
  },
  "demo/docs/hidden-feature.mdx": {
    "inboundLinks": 0,
    "outboundLinks": 1,
    "importedBy": 0,
    "navDepth": null,
    "orphanNav": true,
    "orphanLinks": false,
    "orphanTrue": true,
    "orphanReference": false,
    "deepNav": false,
    "hubScore": 0,
    "deadEnd": false,
    "deadEndScore": 0
  },
  "demo/docs/deep-nav/page1.mdx": {
    "inboundLinks": 1,
    "outboundLinks": 0,
    "importedBy": 0,
    "navDepth": 5,
    "orphanNav": false,
    "orphanLinks": false,
    "orphanTrue": false,
    "orphanReference": false,
    "deepNav": true,
    "hubScore": 1,
    "deadEnd": false,
    "deadEndScore": 1
  },
  "demo/snippets/auth.jsx": {
    "inboundLinks": 0,
    "outboundLinks": 0,
    "importedBy": 2,
    "orphanNav": false,
    "orphanLinks": false,
    "orphanTrue": false,
    "orphanReference": false,
    "deepNav": false,
    "hubScore": 0,
    "deadEnd": false,
    "deadEndScore": 0
  },
  "demo/snippets/login.js": {
    "inboundLinks": 0,
    "outboundLinks": 0,
    "importedBy": 1,
    "orphanNav": false,
    "orphanLinks": false,
    "orphanTrue": false,
    "orphanReference": false,
    "deepNav": false,
    "hubScore": 0,
    "deadEnd": false,
    "deadEndScore": 0
  },
  "demo/snippets/api-call.ts": {
    "inboundLinks": 0,
    "outboundLinks": 0,
    "importedBy": 1,
    "orphanNav": false,
    "orphanLinks": false,
    "orphanTrue": false,
    "orphanReference": false,
    "deepNav": false,
    "hubScore": 0,
    "deadEnd": false,
    "deadEndScore": 0
  },
  "demo/docs/dead-end-page.mdx": {
    "inboundLinks": 8,
    "outboundLinks": 0,
    "importedBy": 0,
    "navDepth": 2,
    "orphanNav": false,
    "orphanLinks": false,
    "orphanTrue": false,
    "orphanReference": false,
    "deepNav": false,
    "hubScore": 8,
    "deadEnd": true,
    "deadEndScore": 8
  },
  "demo/docs/hub-page.mdx": {
    "inboundLinks": 12,
    "outboundLinks": 8,
    "importedBy": 0,
    "navDepth": 2,
    "orphanNav": false,
    "orphanLinks": false,
    "orphanTrue": false,
    "orphanReference": false,
    "deepNav": false,
    "hubScore": 12,
    "deadEnd": false,
    "deadEndScore": 12
  },
  "demo/docs/orphan-page.mdx": {
    "inboundLinks": 0,
    "outboundLinks": 0,
    "importedBy": 0,
    "navDepth": null,
    "orphanNav": true,
    "orphanLinks": true,
    "orphanTrue": true,
    "orphanReference": false,
    "deepNav": false,
    "hubScore": 0,
    "deadEnd": false,
    "deadEndScore": 0
  }
}
